linmo/__init__.py
linmo/plot.py
linmo/resample.py
linmo/simulate.py
linmo-0.0.1.dist-info/METADATA
linmo-0.0.1.dist-info/WHEEL
linmo-0.0.1.dist-info/top_level.txt
linmo-0.0.1.dist-info/RECORD
